mutiny/__init__.py
mutiny/events.py
mutiny/models.py
mutiny/py.typed
mutiny/_internal/__init__.py
mutiny/_internal/authentication_data.py
mutiny/_internal/client.py
mutiny/_internal/event_handler.py
mutiny/_internal/events.py
mutiny/_internal/gateway.py
mutiny/_internal/rest.py
mutiny/_internal/state.py
mutiny/_internal/utils.py
mutiny/_internal/models/__init__.py
mutiny/_internal/models/attachment.py
mutiny/_internal/models/channel.py
mutiny/_internal/models/embed.py
mutiny/_internal/models/message.py
mutiny/_internal/models/permissions.py
mutiny/_internal/models/server.py
mutiny/_internal/models/user.py
mutiny/_internal/models/bases/__init__.py
mutiny/_internal/models/bases/bit_field.py
mutiny/_internal/models/bases/models.py
mutiny-0.3.1a0.dist-info/WHEEL
mutiny-0.3.1a0.dist-info/METADATA
mutiny-0.3.1a0.dist-info/RECORD
