Metadata-Version: 2.1
Name: mutiny
Version: 0.3.1a0
Summary: Async ready API wrapper for Revolt API written in Python.
Author: Jakub Kuczys (jack1142)
Requires-Python: >=3.9,<3.10
Classifier: Development Status :: 3 - Alpha
Classifier: Framework :: AsyncIO
Classifier: Intended Audience :: Developers
Classifier: License :: OSI Approved :: Apache Software License
Classifier: Operating System :: OS Independent
Classifier: Programming Language :: Python :: 3.9
Classifier: Topic :: Internet
Classifier: Topic :: Software Development :: Libraries
Classifier: Topic :: Software Development :: Libraries :: Python Modules
Classifier: Topic :: Utilities
Classifier: Typing :: Typed
Requires-Dist: aiohttp~=3.7
Requires-Dist: ulid-py~=1.0
Requires-Dist: yarl~=1.6
Requires-Dist: black==21.7b0 ; extra == "dev"
Requires-Dist: flake8==3.9.2 ; extra == "dev"
Requires-Dist: isort==5.9.3 ; extra == "dev"
Requires-Dist: mypy==0.910 ; extra == "dev"
Requires-Dist: msgpack-types>=0.2.0 ; extra == "dev"
Requires-Dist: msgpack~=1.0 ; extra == "msgpack"
Project-URL: Documentation, https://mutiny.readthedocs.io
Project-URL: Issue Tracker, https://github.com/jack1142/Mutiny/issues
Project-URL: Source Code, https://github.com/jack1142/Mutiny
Project-URL: Sponsor on GitHub, https://github.com/sponsors/jack1142
Provides-Extra: dev
Provides-Extra: msgpack
